upn2sepa/__init__.py
upn2sepa/convert.py
upn2sepa/run.py
upn2sepa-1.0.1.dist-info/LICENSE
upn2sepa-1.0.1.dist-info/METADATA
upn2sepa-1.0.1.dist-info/WHEEL
upn2sepa-1.0.1.dist-info/entry_points.txt
upn2sepa-1.0.1.dist-info/top_level.txt
upn2sepa-1.0.1.dist-info/RECORD
