Metadata-Version: 2.1
Name: upn2sepa
Version: 1.0.1
Summary: UPN QR to SEPA QR converter.
Home-page: https://github.com/janzmazek/upn2sepa
Author: Jan Zmazek
Author-email: jan.zmazek@gmail.com
License: MIT license
Platform: UNKNOWN
License-File: LICENSE
Requires-Dist: Pillow
Requires-Dist: pyzbar
Requires-Dist: segno
